README.rst
setup.py
src/healthvaultlib/__init__.py
src/healthvaultlib/hvcrypto.py
src/healthvaultlib/exceptions/__init__.py
src/healthvaultlib/exceptions/healthserviceexception.py
src/healthvaultlib/helpers/__init__.py
src/healthvaultlib/helpers/connection.py
src/healthvaultlib/helpers/requestmanager.py
src/healthvaultlib/itemtypes/__init__.py
src/healthvaultlib/itemtypes/advancedirective.py
src/healthvaultlib/itemtypes/aerobicprofile.py
src/healthvaultlib/itemtypes/allergicepisode.py
src/healthvaultlib/itemtypes/allergy.py
src/healthvaultlib/itemtypes/applicationdatareference.py
src/healthvaultlib/itemtypes/appointment.py
src/healthvaultlib/itemtypes/appspecificinformation.py
src/healthvaultlib/itemtypes/asthmainhaler.py
src/healthvaultlib/itemtypes/asthmainhalerusage.py
src/healthvaultlib/itemtypes/basicdemographicinformation.py
src/healthvaultlib/itemtypes/bloodglucose.py
src/healthvaultlib/itemtypes/bloodoxygensaturation.py
src/healthvaultlib/itemtypes/bloodpressure.py
src/healthvaultlib/itemtypes/bodycomposition.py
src/healthvaultlib/itemtypes/bodydimension.py
src/healthvaultlib/itemtypes/calorieguideline.py
src/healthvaultlib/itemtypes/cardiacprofile.py
src/healthvaultlib/itemtypes/careplan.py
src/healthvaultlib/itemtypes/cholesterol.py
src/healthvaultlib/itemtypes/clinicaldocumentarchitecture.py
src/healthvaultlib/itemtypes/comment.py
src/healthvaultlib/itemtypes/concern.py
src/healthvaultlib/itemtypes/condition.py
src/healthvaultlib/itemtypes/contact.py
src/healthvaultlib/itemtypes/continuityofcaredocument.py
src/healthvaultlib/itemtypes/continuityofcarerecord.py
src/healthvaultlib/itemtypes/contraindication.py
src/healthvaultlib/itemtypes/dailydietaryintake.py
src/healthvaultlib/itemtypes/dailymedicationusage.py
src/healthvaultlib/itemtypes/defibrillatorepisode.py
src/healthvaultlib/itemtypes/diabeticprofile.py
src/healthvaultlib/itemtypes/dischargesummary.py
src/healthvaultlib/itemtypes/educationdocument.py
src/pyhealthvault.egg-info/PKG-INFO
src/pyhealthvault.egg-info/SOURCES.txt
src/pyhealthvault.egg-info/dependency_links.txt
src/pyhealthvault.egg-info/requires.txt
src/pyhealthvault.egg-info/top_level.txt