Metadata-Version: 1.1
Name: pyhealthvault
Version: 1.0
Summary: Python SDK for HealthVault
Home-page: https://github.com/rajeevs1992/pyhealthvault
Author: Rajeev S
Author-email: rajeevs1992@gmail.com
License: MIT
Download-URL: https://github.com/rajeevs1992/pyhealthvault/archive/master.zip
Platform: UNKNOWN
